jvserve/__init__.py
jvserve/cli.py
jvserve/lib/__init__.py
jvserve/lib/agent_interface.py
jvserve/lib/agent_pulse.py
jvserve/lib/file_interface.py
jvserve/lib/jac_interface.py
jvserve/lib/jvlogger.py
jvserve-2.1.25.dist-info/licenses/LICENSE
jvserve-2.1.25.dist-info/METADATA
jvserve-2.1.25.dist-info/WHEEL
jvserve-2.1.25.dist-info/entry_points.txt
jvserve-2.1.25.dist-info/top_level.txt
jvserve-2.1.25.dist-info/RECORD
