Metadata-Version: 2.4
Name: jvserve
Version: 2.1.25
Summary: FastAPI webserver for loading and interaction with JIVAS agents.
Home-page: https://github.com/TrueSelph/jvserve
Author: TrueSelph Inc.
Author-email: admin@trueselph.com
Keywords: jivas
Requires-Python: >=3.12.0
License-File: LICENSE
Requires-Dist: jac-cloud==0.2.7
Requires-Dist: jaclang==0.8.7
Requires-Dist: psutil>=7.0.0
Requires-Dist: pyaml==25.7.0
Requires-Dist: requests==2.32.5
Requires-Dist: aiohttp==3.13.1
Requires-Dist: schedule==1.2.2
Requires-Dist: boto3==1.40.59
Requires-Dist: sniffio
Provides-Extra: dev
Requires-Dist: pre-commit; extra == "dev"
Requires-Dist: pytest; extra == "dev"
Requires-Dist: pytest-mock; extra == "dev"
Requires-Dist: pytest-cov; extra == "dev"
Requires-Dist: coverage; extra == "dev"
Dynamic: author
Dynamic: author-email
Dynamic: description
Dynamic: description-content-type
Dynamic: home-page
Dynamic: keywords
Dynamic: license-file
Dynamic: provides-extra
Dynamic: requires-dist
Dynamic: requires-python
Dynamic: summary
